nope/__init__.py
nope/main.py
extension_swap-0.0.8.dist-info/LICENSE
extension_swap-0.0.8.dist-info/METADATA
extension_swap-0.0.8.dist-info/WHEEL
extension_swap-0.0.8.dist-info/entry_points.txt
extension_swap-0.0.8.dist-info/top_level.txt
extension_swap-0.0.8.dist-info/RECORD
