Metadata-Version: 2.1
Name: extension-swap
Version: 0.0.8
Summary: change file extension to nope and back to .tf (for terraform resource wiping)
Home-page: https://bitbucket.org/rednap/extension-swap
Author: Andy Klier
Author-email: andyklier@gmail.com
License: UNKNOWN
Platform: UNKNOWN
Classifier: Programming Language :: Python :: 3
Classifier: License :: OSI Approved :: MIT License
Classifier: Operating System :: OS Independent
Requires-Dist: setuptools
